[
  {
    "id": "AC1 041191",
    "content": "PT-AU09",
    "start": "2016-01-08 20:51",
    "end": "2016-01-09 01:47"
  },
  {
    "id": "AC1 041192",
    "content": "PT-AU41",
    "start": "2016-01-09 03:29",
    "end": "2016-01-09 12:05"
  },
  {
    "id": "AC1 041193",
    "content": "PT-AU04",
    "start": "2016-01-09 14:51",
    "end": "2016-01-09 21:40"
  },
  {
    "id": "AC1 041195",
    "content": "PT-AU44",
    "start": "2016-01-12 04:18",
    "end": "2016-01-12 12:52"
  },
  {
    "id": "AC1 041196",
    "content": "PT-AU09",
    "start": "2016-01-12 14:00",
    "end": "2016-01-12 19:08"
  },
  {
    "id": "AC1 041197",
    "content": "PT-AU44",
    "start": "2016-01-13 02:37",
    "end": "2016-01-13 11:44"
  },
  {
    "id": "AC1 041199",
    "content": "PT-AU08",
    "start": "2016-01-13 14:18",
    "end": "2016-01-13 21:18"
  },
  {
    "id": "AC1 041200",
    "content": "PT-AU41",
    "start": "2016-01-14 02:40",
    "end": "2016-01-14 11:16"
  },
  {
    "id": "AC1 041201",
    "content": "PT-AU04",
    "start": "2016-01-14 13:00",
    "end": "2016-01-14 20:29"
  },
  {
    "id": "AC1 041202",
    "content": "PT-AU44",
    "start": "2016-01-15 02:33",
    "end": "2016-01-15 11:18"
  },
  {
    "id": "AC1 041203",
    "content": "PT-AU04",
    "start": "2016-01-15 16:23",
    "end": "2016-01-16 00:05"
  },
  {
    "id": "AC1 041204",
    "content": "PT-AU44",
    "start": "2016-01-16 02:21",
    "end": "2016-01-16 10:19"
  },
  {
    "id": "AC1 041205",
    "content": "PT-AU08",
    "start": "2016-01-16 14:56",
    "end": "2016-01-16 21:45"
  },
  {
    "id": "AC1 041208",
    "content": "PT-AU44",
    "start": "2016-01-18 18:46",
    "end": "2016-01-19 03:33"
  },
  {
    "id": "AC1 041210",
    "content": "PT-AU44",
    "start": "2016-01-19 18:03",
    "end": "2016-01-20 02:19"
  },
  {
    "id": "AC1 041211",
    "content": "PT-AU44",
    "start": "2016-01-20 19:03",
    "end": "2016-01-20 19:12"
  },
  {
    "id": "AC1 041212",
    "content": "PT-AU04",
    "start": "2016-01-21 05:55",
    "end": "2016-01-21 13:21"
  },
  {
    "id": "AC1 041213",
    "content": "PT-AU41",
    "start": "2016-01-21 18:42",
    "end": "2016-01-22 03:39"
  },
  {
    "id": "AC1 041214",
    "content": "PT-AU41",
    "start": "2016-01-22 05:03",
    "end": "2016-01-22 12:46"
  },
  {
    "id": "AC1 041215",
    "content": "PT-AU44",
    "start": "2016-01-22 18:18",
    "end": "2016-01-23 02:31"
  },
  {
    "id": "AC1 041216",
    "content": "PT-AU41",
    "start": "2016-01-23 05:39",
    "end": "2016-01-23 13:26"
  },
  {
    "id": "AC1 041217",
    "content": "PT-AU08",
    "start": "2016-01-23 16:18",
    "end": "2016-01-23 22:51"
  },
  {
    "id": "AC1 041219",
    "content": "PT-AU44",
    "start": "2016-01-25 18:25",
    "end": "2016-01-26 03:25"
  },
  {
    "id": "AC1 041220",
    "content": "PT-AU03",
    "start": "2016-01-26 04:44",
    "end": "2016-01-26 11:30"
  },
  {
    "id": "AC1 041224",
    "content": "PT-AU44",
    "start": "2016-01-27 19:41",
    "end": "2016-01-28 04:26"
  },
  {
    "id": "AC1 041225",
    "content": "PT-AU04",
    "start": "2016-01-28 05:52",
    "end": "2016-01-28 13:54"
  },
  {
    "id": "AC1 041226",
    "content": "PT-AU44",
    "start": "2016-01-28 18:22",
    "end": "2016-01-29 02:44"
  },
  {
    "id": "AC1 041228",
    "content": "PT-AU44",
    "start": "2016-01-29 18:14",
    "end": "2016-01-30 03:04"
  },
  {
    "id": "AC1 041230",
    "content": "PT-AU08",
    "start": "2016-01-30 16:10",
    "end": "2016-01-30 22:30"
  },
  {
    "id": "AC1 041231",
    "content": "PT-AU 28",
    "start": "2016-02-01 00:21",
    "end": "2016-02-01 06:38"
  },
  {
    "id": "AC1 041234",
    "content": "PT-AU44",
    "start": "2016-02-02 02:13",
    "end": "2016-02-02 10:32"
  },
  {
    "id": "AC1 041235",
    "content": "PT-AU41",
    "start": "2016-02-02 11:50",
    "end": "2016-02-02 18:17"
  },
  {
    "id": "AC1 041236",
    "content": "PT-AU31",
    "start": "2016-02-03 02:47",
    "end": "2016-02-03 11:23"
  },
  {
    "id": "AC1 041237",
    "content": "PT-AU04",
    "start": "2016-02-03 14:46",
    "end": "2016-02-03 21:16"
  },
  {
    "id": "AC1 041238",
    "content": "PT-AU09",
    "start": "2016-02-03 22:51",
    "end": "2016-02-04 03:41"
  },
  {
    "id": "AC1 041239",
    "content": "PT-AU44",
    "start": "2016-02-04 05:40",
    "end": "2016-02-04 13:33"
  },
  {
    "id": "AC1 041240",
    "content": "PT-AU08",
    "start": "2016-02-04 15:31",
    "end": "2016-02-04 21:43"
  },
  {
    "id": "AC1 041241",
    "content": "PT-AU44",
    "start": "2016-02-05 02:24",
    "end": "2016-02-05 11:23"
  },
  {
    "id": "AC1 041242",
    "content": "PT-AU04",
    "start": "2016-02-05 15:11",
    "end": "2016-02-05 22:31"
  },
  {
    "id": "AC1 041243",
    "content": "PT-AU44",
    "start": "2016-02-06 03:05",
    "end": "2016-02-06 11:24"
  },
  {
    "id": "AC1 041244",
    "content": "PT-AU47",
    "start": "2016-02-06 13:13",
    "end": "2016-02-06 22:29"
  },
  {
    "id": "AC1 041245",
    "content": "PT-AU17",
    "start": "2016-02-07 23:35",
    "end": "2016-02-07 23:37"
  },
  {
    "id": "AC1 041246",
    "content": "PT-AU03",
    "start": "2016-02-08 16:55",
    "end": "2016-02-08 22:33"
  },
  {
    "id": "AC1 041247",
    "content": "PT-AU44",
    "start": "2016-02-09 02:45",
    "end": "2016-02-09 11:41"
  },
  {
    "id": "AC1 041248",
    "content": "PT-AU04",
    "start": "2016-02-09 16:31",
    "end": "2016-02-09 23:26"
  },
  {
    "id": "AC1 041249",
    "content": "PT-AU44",
    "start": "2016-02-10 02:18",
    "end": "2016-02-10 11:02"
  },
  {
    "id": "AC1 041251",
    "content": "PT-AU08",
    "start": "2016-02-10 15:16",
    "end": "2016-02-10 22:46"
  },
  {
    "id": "AC1 041252",
    "content": "PT-AU44",
    "start": "2016-02-11 02:23",
    "end": "2016-02-11 10:49"
  },
  {
    "id": "AC1 041253",
    "content": "PT-AU08",
    "start": "2016-02-11 12:19",
    "end": "2016-02-11 18:56"
  },
  {
    "id": "AC1 041254",
    "content": "PT-AU44",
    "start": "2016-02-12 02:31",
    "end": "2016-02-12 10:45"
  },
  {
    "id": "AC1 041255",
    "content": "PT-AU08",
    "start": "2016-02-12 12:05",
    "end": "2016-02-12 18:06"
  },
  {
    "id": "AC1 041256",
    "content": "PT-AU44",
    "start": "2016-02-13 02:13",
    "end": "2016-02-13 10:56"
  },
  {
    "id": "AC1 041257",
    "content": "PT-AU41",
    "start": "2016-02-13 14:19",
    "end": "2016-02-13 22:18"
  },
  {
    "id": "AC1 041260",
    "content": "PT-AU44",
    "start": "2016-02-15 18:57",
    "end": "2016-02-16 03:29"
  },
  {
    "id": "AC1 041262",
    "content": "PT-AU41",
    "start": "2016-02-16 20:03",
    "end": "2016-02-17 05:10"
  },
  {
    "id": "AC1 041263",
    "content": "PT-AU17",
    "start": "2016-02-17 06:18",
    "end": "2016-02-17 17:58"
  },
  {
    "id": "AC1 041264",
    "content": "PT-AU44",
    "start": "2016-02-17 21:16",
    "end": "2016-02-18 05:00"
  },
  {
    "id": "AC1 041265",
    "content": "PT-AU08",
    "start": "2016-02-18 06:12",
    "end": "2016-02-18 13:11"
  },
  {
    "id": "AC1 041266",
    "content": "PT-AU44",
    "start": "2016-02-18 19:02",
    "end": "2016-02-19 04:10"
  },
  {
    "id": "AC1 041267",
    "content": "PT-AU41",
    "start": "2016-02-19 06:51",
    "end": "2016-02-19 15:24"
  },
  {
    "id": "AC1 041268",
    "content": "PT-AU41",
    "start": "2016-02-19 19:34",
    "end": "2016-02-20 03:46"
  },
  {
    "id": "AC1 041269",
    "content": "PT-AU04",
    "start": "2016-02-20 05:26",
    "end": "2016-02-20 11:55"
  },
  {
    "id": "AC1 041270",
    "content": "PT-AU42",
    "start": "2016-02-20 13:28",
    "end": "2016-02-20 19:57"
  },
  {
    "id": "AC1 041272",
    "content": "PT-AU44",
    "start": "2016-02-22 18:48",
    "end": "2016-02-23 03:36"
  },
  {
    "id": "AC1 041274",
    "content": "PT-AU44",
    "start": "2016-02-23 19:15",
    "end": "2016-02-24 03:31"
  },
  {
    "id": "AC1 041275",
    "content": "PT-AU08",
    "start": "2016-02-24 05:01",
    "end": "2016-02-24 11:38"
  },
  {
    "id": "AC1 041276",
    "content": "PT-AU44",
    "start": "2016-02-24 19:03",
    "end": "2016-02-25 04:04"
  },
  {
    "id": "AC1 041277",
    "content": "PT-AU41",
    "start": "2016-02-25 05:47",
    "end": "2016-02-25 13:34"
  },
  {
    "id": "AC1 041278",
    "content": "PT-AU44",
    "start": "2016-02-25 18:40",
    "end": "2016-02-26 03:55"
  },
  {
    "id": "AC1 041279",
    "content": "PT-AU04",
    "start": "2016-02-26 05:38",
    "end": "2016-02-26 13:04"
  },
  {
    "id": "AC1 041280",
    "content": "PT-AU44",
    "start": "2016-02-26 18:11",
    "end": "2016-02-27 02:55"
  },
  {
    "id": "AC1 041282",
    "content": "PT-AU41",
    "start": "2016-02-29 08:29",
    "end": "2016-02-29 15:52"
  },
  {
    "id": "AC1 041285",
    "content": "PT-AU44",
    "start": "2016-03-01 03:01",
    "end": "2016-03-01 11:40"
  },
  {
    "id": "AC1 041287",
    "content": "PT-AU11",
    "start": "2016-03-01 13:05",
    "end": "2016-03-01 20:42"
  },
  {
    "id": "AC1 041288",
    "content": "PT-AU44",
    "start": "2016-03-02 03:04",
    "end": "2016-03-02 11:09"
  },
  {
    "id": "AC1 041290",
    "content": "PT-AU44",
    "start": "2016-03-03 02:20",
    "end": "2016-03-03 10:39"
  },
  {
    "id": "AC1 041292",
    "content": "PT-AU44",
    "start": "2016-03-04 02:34",
    "end": "2016-03-04 11:01"
  },
  {
    "id": "AC1 041293",
    "content": "PT-AU08",
    "start": "2016-03-04 15:09",
    "end": "2016-03-04 21:16"
  },
  {
    "id": "AC1 041294",
    "content": "PT-AU44",
    "start": "2016-03-05 02:11",
    "end": "2016-03-05 10:30"
  },
  {
    "id": "AC1 041295",
    "content": "PT-AU19",
    "start": "2016-03-05 12:36",
    "end": "2016-03-05 22:03"
  },
  {
    "id": "AC1 041296",
    "content": "PT-AU41",
    "start": "2016-03-07 01:21",
    "end": "2016-03-07 01:45"
  },
  {
    "id": "AC1 041297",
    "content": "PT-AU03",
    "start": "2016-03-07 16:34",
    "end": "2016-03-07 22:38"
  },
  {
    "id": "AC1 041298",
    "content": "PT-AU44",
    "start": "2016-03-08 02:42",
    "end": "2016-03-08 10:38"
  },
  {
    "id": "AC1 041300",
    "content": "PT-AU44",
    "start": "2016-03-09 02:51",
    "end": "2016-03-09 11:16"
  },
  {
    "id": "AC1 041301",
    "content": "PT-AU08",
    "start": "2016-03-09 12:33",
    "end": "2016-03-09 18:57"
  },
  {
    "id": "AC1 041302",
    "content": "PT-AU44",
    "start": "2016-03-10 02:18",
    "end": "2016-03-10 10:35"
  },
  {
    "id": "AC1 041303",
    "content": "PT-AU11",
    "start": "2016-03-10 12:12",
    "end": "2016-03-10 19:58"
  },
  {
    "id": "AC1 041305",
    "content": "PT-AU44",
    "start": "2016-03-11 02:37",
    "end": "2016-03-11 10:23"
  },
  {
    "id": "AC1 041306",
    "content": "PT-AU08",
    "start": "2016-03-11 11:48",
    "end": "2016-03-11 17:34"
  },
  {
    "id": "AC1 041307",
    "content": "PT-AU44",
    "start": "2016-03-12 02:19",
    "end": "2016-03-12 10:57"
  },
  {
    "id": "AC1 041308",
    "content": "PT-AU44",
    "start": "2016-03-12 13:05",
    "end": "2016-03-12 19:52"
  },
  {
    "id": "AC1 041309",
    "content": "PT-AU 28",
    "start": "2016-03-14 00:53",
    "end": "2016-03-14 07:06"
  },
  {
    "id": "AC1 041311",
    "content": "PT-AU44",
    "start": "2016-03-14 18:07",
    "end": "2016-03-15 02:45"
  },
  {
    "id": "AC1 041312",
    "content": "PT-AU41",
    "start": "2016-03-15 05:20",
    "end": "2016-03-15 12:55"
  },
  {
    "id": "AC1 041313",
    "content": "PT-AU44",
    "start": "2016-03-15 18:03",
    "end": "2016-03-16 02:21"
  },
  {
    "id": "AC1 041314",
    "content": "PT-AU08",
    "start": "2016-03-16 03:31",
    "end": "2016-03-16 10:32"
  },
  {
    "id": "AC1 041315",
    "content": "PT-AU44",
    "start": "2016-03-16 17:57",
    "end": "2016-03-17 01:49"
  },
  {
    "id": "AC1 041317",
    "content": "PT-AU44",
    "start": "2016-03-17 18:40",
    "end": "2016-03-18 03:38"
  },
  {
    "id": "AC1 041319",
    "content": "PT-AU44",
    "start": "2016-03-18 17:57",
    "end": "2016-03-19 03:02"
  },
  {
    "id": "AC1 041320",
    "content": "PT-AU41",
    "start": "2016-03-19 06:31",
    "end": "2016-03-19 14:22"
  },
  {
    "id": "AC1 041323",
    "content": "PT-AU44",
    "start": "2016-03-28 18:22",
    "end": "2016-03-29 02:35"
  },
  {
    "id": "AC1 041324",
    "content": "PT-AU03",
    "start": "2016-03-29 03:56",
    "end": "2016-03-29 10:55"
  },
  {
    "id": "AC1 041325",
    "content": "PT-AU44",
    "start": "2016-03-29 17:44",
    "end": "2016-03-30 01:58"
  },
  {
    "id": "AC1 041327",
    "content": "PT-AU44",
    "start": "2016-03-30 18:21",
    "end": "2016-03-31 03:14"
  },
  {
    "id": "AC1 041329",
    "content": "PT-AU44",
    "start": "2016-03-31 18:16",
    "end": "2016-04-01 02:33"
  },
  {
    "id": "AC1 041330",
    "content": "PT-AU41",
    "start": "2016-04-01 04:09",
    "end": "2016-04-01 11:55"
  },
  {
    "id": "AC1 041331",
    "content": "PT-AU44",
    "start": "2016-04-01 18:02",
    "end": "2016-04-02 02:43"
  },
  {
    "id": "AC1 041332",
    "content": "PT-AU41",
    "start": "2016-04-02 03:55",
    "end": "2016-04-02 10:20"
  },
  {
    "id": "AC1 041334",
    "content": "PT-AU11",
    "start": "2016-04-03 23:34",
    "end": "2016-04-03 23:41"
  },
  {
    "id": "AC1 041335",
    "content": "PT-AU09",
    "start": "2016-04-04 14:27",
    "end": "2016-04-04 19:20"
  },
  {
    "id": "AC1 041336",
    "content": "PT-AU44",
    "start": "2016-04-05 02:41",
    "end": "2016-04-05 11:18"
  },
  {
    "id": "AC1 041338",
    "content": "PT-AU44",
    "start": "2016-04-06 02:28",
    "end": "2016-04-06 11:23"
  },
  {
    "id": "AC1 041340",
    "content": "PT-AU09",
    "start": "2016-04-06 20:34",
    "end": "2016-04-07 01:20"
  },
  {
    "id": "AC1 041341",
    "content": "PT-AU44",
    "start": "2016-04-07 03:18",
    "end": "2016-04-07 03:26"
  },
  {
    "id": "AC1 041342",
    "content": "PT-AU11",
    "start": "2016-04-07 13:47",
    "end": "2016-04-07 21:31"
  },
  {
    "id": "AC1 041344",
    "content": "PT-AU17",
    "start": "2016-04-08 13:28",
    "end": "2016-04-08 23:52"
  },
  {
    "id": "AC1 041348",
    "content": "PT-AU44",
    "start": "2016-04-12 02:23",
    "end": "2016-04-12 11:13"
  },
  {
    "id": "AC1 041351",
    "content": "PT-AU44",
    "start": "2016-04-13 02:42",
    "end": "2016-04-13 11:13"
  },
  {
    "id": "AC1 041352",
    "content": "PT-AU08",
    "start": "2016-04-13 12:34",
    "end": "2016-04-13 18:10"
  },
  {
    "id": "AC1 041353",
    "content": "PT-AU44",
    "start": "2016-04-14 02:19",
    "end": "2016-04-14 10:43"
  },
  {
    "id": "AC1 041354",
    "content": "PT-AU11",
    "start": "2016-04-14 12:44",
    "end": "2016-04-14 20:55"
  },
  {
    "id": "AC1 041355",
    "content": "PT-AU44",
    "start": "#N/A",
    "end": "#N/A"
  },
  {
    "id": "AC1 041357",
    "content": "PT-AU47",
    "start": "2016-04-15 12:17",
    "end": "2016-04-15 22:00"
  },
  {
    "id": "AC1 041358",
    "content": "PT-AU44",
    "start": "2016-04-16 02:23",
    "end": "2016-04-16 10:57"
  },
  {
    "id": "AC1 041359",
    "content": "PT-AU44",
    "start": "2016-04-16 13:11",
    "end": "2016-04-16 19:48"
  },
  {
    "id": "AC1 041360",
    "content": "PT-AU08",
    "start": "2016-04-18 00:12",
    "end": "2016-04-18 07:11"
  },
  {
    "id": "AC1 041361",
    "content": "PT-AU44",
    "start": "2016-04-18 18:38",
    "end": "2016-04-19 02:44"
  },
  {
    "id": "AC1 041362",
    "content": "PT-AU41",
    "start": "2016-04-19 04:15",
    "end": "2016-04-19 12:14"
  },
  {
    "id": "AC1 041363",
    "content": "PT-AU44",
    "start": "2016-04-19 18:12",
    "end": "2016-04-20 03:16"
  },
  {
    "id": "AC1 041364",
    "content": "PT-AU41",
    "start": "2016-04-20 04:20",
    "end": "2016-04-20 11:09"
  },
  {
    "id": "AC1 041365",
    "content": "PT-AU44",
    "start": "2016-04-20 17:54",
    "end": "2016-04-21 02:19"
  },
  {
    "id": "AC1 041367",
    "content": "PT-AU44",
    "start": "2016-04-21 18:21",
    "end": "2016-04-22 02:59"
  },
  {
    "id": "AC1 041368",
    "content": "PT-AU47",
    "start": "2016-04-22 04:33",
    "end": "2016-04-22 13:31"
  },
  {
    "id": "AC1 041369",
    "content": "PT-AU44",
    "start": "2016-04-22 17:51",
    "end": "2016-04-23 01:44"
  },
  {
    "id": "AC1 041370",
    "content": "PT-AU04",
    "start": "2016-04-23 03:54",
    "end": "2016-04-23 10:52"
  },
  {
    "id": "AC1 041371",
    "content": "PT-AU41",
    "start": "2016-04-23 13:53",
    "end": "2016-04-23 21:30"
  },
  {
    "id": "AC1 041372",
    "content": "PT-AU11",
    "start": "2016-04-25 00:49",
    "end": "2016-04-25 01:06"
  },
  {
    "id": "AC1 041373",
    "content": "PT-AU44",
    "start": "2016-04-25 18:38",
    "end": "2016-04-26 03:33"
  },
  {
    "id": "AC1 041374",
    "content": "PT-AU41",
    "start": "2016-04-26 17:51",
    "end": "2016-04-27 02:16"
  },
  {
    "id": "AC1 041375",
    "content": "PT-AU44",
    "start": "2016-04-27 05:07",
    "end": "2016-04-27 13:00"
  },
  {
    "id": "AC1 041376",
    "content": "PT-AU44",
    "start": "2016-04-27 17:50",
    "end": "2016-04-28 02:44"
  },
  {
    "id": "AC1 041377",
    "content": "PT-AU41",
    "start": "2016-04-28 03:49",
    "end": "2016-04-28 10:41"
  },
  {
    "id": "AC1 041378",
    "content": "PT-AU09",
    "start": "2016-04-28 12:16",
    "end": "2016-04-28 17:04"
  },
  {
    "id": "AC1 041379",
    "content": "PT-AU44",
    "start": "2016-04-28 18:54",
    "end": "2016-04-29 02:46"
  },
  {
    "id": "AC1 041380",
    "content": "PT-AU19",
    "start": "2016-04-29 10:26",
    "end": "2016-04-29 20:40"
  },
  {
    "id": "AC1 041381",
    "content": "PT-AU44",
    "start": "2016-04-29 22:12",
    "end": "2016-04-30 06:42"
  },
  {
    "id": "AC1 041382",
    "content": "PT-AU47",
    "start": "2016-04-30 10:00",
    "end": "2016-04-30 19:59"
  },
  {
    "id": "AC1 041383",
    "content": "PT-AU09",
    "start": "2016-05-01 23:41",
    "end": "2016-05-02 04:35"
  },
  {
    "id": "AC1 041385",
    "content": "PT-AU03",
    "start": "2016-05-03 16:00",
    "end": "2016-05-03 21:56"
  },
  {
    "id": "AC1 041386",
    "content": "PT-AU44",
    "start": "2016-05-04 02:47",
    "end": "2016-05-04 11:29"
  },
  {
    "id": "AC1 041387",
    "content": "PT-AU41",
    "start": "2016-05-04 18:36",
    "end": "2016-05-05 02:38"
  },
  {
    "id": "AC1 041388",
    "content": "PT-AU44",
    "start": "2016-05-05 04:37",
    "end": "2016-05-05 13:03"
  },
  {
    "id": "AC1 041389",
    "content": "PT-AU08",
    "start": "2016-05-05 14:02",
    "end": "2016-05-05 19:26"
  },
  {
    "id": "AC1 041390",
    "content": "PT-AU44",
    "start": "2016-05-06 02:31",
    "end": "2016-05-06 10:52"
  },
  {
    "id": "AC1 041391",
    "content": "PT-AU08",
    "start": "2016-05-06 12:01",
    "end": "2016-05-06 17:36"
  },
  {
    "id": "AC1 041392",
    "content": "PT-AU44",
    "start": "2016-05-07 02:22",
    "end": "2016-05-07 11:02"
  },
  {
    "id": "AC1 041393",
    "content": "PT-AU44",
    "start": "2016-05-07 12:18",
    "end": "2016-05-07 22:54"
  },
  {
    "id": "AC1 041397",
    "content": "PT-AU44",
    "start": "2016-05-10 02:13",
    "end": "2016-05-10 10:15"
  },
  {
    "id": "AC1 041398",
    "content": "PT-AU11",
    "start": "2016-05-10 11:22",
    "end": "2016-05-10 19:18"
  },
  {
    "id": "AC1 041399",
    "content": "PT-AU44",
    "start": "2016-05-11 02:48",
    "end": "2016-05-11 11:40"
  },
  {
    "id": "AC1 041400",
    "content": "PT-AU08",
    "start": "2016-05-11 12:50",
    "end": "2016-05-11 19:13"
  },
  {
    "id": "AC1 041401",
    "content": "PT-AU44",
    "start": "2016-05-12 02:30",
    "end": "2016-05-12 11:04"
  },
  {
    "id": "AC1 041402",
    "content": "PT-AU19",
    "start": "2016-05-12 12:14",
    "end": "2016-05-12 21:49"
  },
  {
    "id": "AC1 041403",
    "content": "PT-AU44",
    "start": "2016-05-13 02:34",
    "end": "2016-05-13 11:10"
  },
  {
    "id": "AC1 041405",
    "content": "PT-AU44",
    "start": "2016-05-14 02:10",
    "end": "2016-05-14 10:33"
  },
  {
    "id": "AC1 041407",
    "content": "PT-AU17",
    "start": "2016-05-15 07:40",
    "end": "2016-05-15 18:43"
  },
  {
    "id": "AC1 041408",
    "content": "PT-AU44",
    "start": "2016-05-17 18:42",
    "end": "2016-05-18 03:27"
  },
  {
    "id": "AC1 041409",
    "content": "PT-AU41",
    "start": "2016-05-18 05:09",
    "end": "2016-05-18 12:41"
  },
  {
    "id": "AC1 041410",
    "content": "PT-AU44",
    "start": "2016-05-18 18:31",
    "end": "2016-05-19 03:05"
  },
  {
    "id": "AC1 041411",
    "content": "PT-AU41",
    "start": "2016-05-19 04:45",
    "end": "2016-05-19 11:49"
  },
  {
    "id": "AC1 041412",
    "content": "PT-AU44",
    "start": "2016-05-19 18:45",
    "end": "2016-05-20 03:46"
  },
  {
    "id": "AC1 041414",
    "content": "PT-AU44",
    "start": "2016-05-20 18:36",
    "end": "2016-05-21 02:59"
  },
  {
    "id": "AC1 041416",
    "content": "PT-AU08",
    "start": "2016-05-21 16:37",
    "end": "2016-05-21 22:44"
  },
  {
    "id": "AC1 041419",
    "content": "PT-AU44",
    "start": "2016-05-23 18:13",
    "end": "2016-05-24 02:52"
  },
  {
    "id": "AC1 041420",
    "content": "PT-AU09",
    "start": "2016-05-24 04:09",
    "end": "2016-05-24 09:17"
  },
  {
    "id": "AC1 041421",
    "content": "PT-AU44",
    "start": "2016-05-24 18:24",
    "end": "2016-05-25 02:49"
  },
  {
    "id": "AC1 041422",
    "content": "PT-AU41",
    "start": "2016-05-25 04:30",
    "end": "2016-05-25 12:37"
  },
  {
    "id": "AC1 041423",
    "content": "PT-AU44",
    "start": "2016-05-25 18:08",
    "end": "2016-05-26 03:09"
  },
  {
    "id": "AC1 041424",
    "content": "PT-AU09",
    "start": "2016-05-26 04:44",
    "end": "2016-05-26 10:01"
  },
  {
    "id": "AC1 041425",
    "content": "PT-AU44",
    "start": "2016-05-26 17:51",
    "end": "2016-05-27 02:20"
  },
  {
    "id": "AC1 041427",
    "content": "PT-AU44",
    "start": "2016-05-27 18:53",
    "end": "2016-05-28 04:02"
  },
  {
    "id": "AC1 041428",
    "content": "PT-AU41",
    "start": "2016-05-28 05:56",
    "end": "2016-05-28 13:33"
  },
  {
    "id": "AC1 041430",
    "content": "PT-AU17",
    "start": "2016-05-29 23:35",
    "end": "2016-05-30 10:40"
  },
  {
    "id": "AC1 041431",
    "content": "PT-AU42",
    "start": "2016-05-30 13:56",
    "end": "2016-05-30 20:11"
  },
  {
    "id": "AC1 041432",
    "content": "PT-AU44",
    "start": "2016-05-31 03:59",
    "end": "2016-05-31 12:29"
  },
  {
    "id": "AC1 041434",
    "content": "PT-AU44",
    "start": "2016-06-01 02:28",
    "end": "2016-06-01 10:15"
  },
  {
    "id": "AC1 041435",
    "content": "PT-AU08",
    "start": "2016-06-01 11:40",
    "end": "2016-06-01 17:46"
  },
  {
    "id": "AC1 041436",
    "content": "PT-AU44",
    "start": "2016-06-02 02:44",
    "end": "2016-06-02 11:20"
  },
  {
    "id": "AC1 041437",
    "content": "PT-AU44",
    "start": "2016-06-02 15:17",
    "end": "2016-06-02 15:27"
  },
  {
    "id": "AC1 041438",
    "content": "PT-AU44",
    "start": "2016-06-03 02:19",
    "end": "2016-06-03 10:43"
  },
  {
    "id": "AC1 041439",
    "content": "PT-AU44",
    "start": "2016-06-03 13:49",
    "end": "2016-06-03 20:17"
  },
  {
    "id": "AC1 041440",
    "content": "PT-AU44",
    "start": "2016-06-04 02:33",
    "end": "2016-06-04 10:40"
  },
  {
    "id": "AC1 041445",
    "content": "PT-AU44",
    "start": "2016-06-07 03:15",
    "end": "2016-06-07 11:44"
  },
  {
    "id": "AC1 041446",
    "content": "PT-AU44",
    "start": "2016-06-07 13:33",
    "end": "2016-06-07 19:45"
  },
  {
    "id": "AC1 041447",
    "content": "PT-AU44",
    "start": "2016-06-08 02:22",
    "end": "2016-06-08 10:40"
  },
  {
    "id": "AC1 041448",
    "content": "PT-AU09",
    "start": "2016-06-08 18:55",
    "end": "2016-06-09 00:04"
  },
  {
    "id": "AC1 041449",
    "content": "PT-AU44",
    "start": "2016-06-09 02:42",
    "end": "2016-06-09 11:16"
  },
  {
    "id": "AC1 041450",
    "content": "PT-AU44",
    "start": "2016-06-10 02:34",
    "end": "2016-06-10 10:43"
  },
  {
    "id": "AC1 041451",
    "content": "PT-AU47",
    "start": "2016-06-10 13:33",
    "end": "2016-06-10 23:21"
  },
  {
    "id": "AC1 041452",
    "content": "PT-AU44",
    "start": "2016-06-11 02:27",
    "end": "2016-06-11 11:11"
  },
  {
    "id": "AC1 041454",
    "content": "PT-AU41",
    "start": "2016-06-13 02:14",
    "end": "2016-06-13 10:13"
  },
  {
    "id": "AC1 041455",
    "content": "PT-AU44",
    "start": "2016-06-13 18:19",
    "end": "2016-06-14 04:09"
  },
  {
    "id": "AC1 041456",
    "content": "PT-AU41",
    "start": "2016-06-14 05:28",
    "end": "2016-06-14 13:28"
  },
  {
    "id": "AC1 041457",
    "content": "PT-AU44",
    "start": "2016-06-14 19:19",
    "end": "2016-06-15 03:26"
  },
  {
    "id": "AC1 041458",
    "content": "PT-AU08",
    "start": "2016-06-15 04:56",
    "end": "2016-06-15 11:29"
  },
  {
    "id": "AC1 041459",
    "content": "PT-AU44",
    "start": "2016-06-15 18:14",
    "end": "2016-06-16 03:07"
  },
  {
    "id": "AC1 041460",
    "content": "PT-AU41",
    "start": "2016-06-16 04:58",
    "end": "2016-06-16 12:41"
  },
  {
    "id": "AC1 041461",
    "content": "PT-AU44",
    "start": "2016-06-16 19:17",
    "end": "2016-06-17 03:50"
  },
  {
    "id": "AC1 041463",
    "content": "PT-AU44",
    "start": "2016-06-17 18:51",
    "end": "2016-06-18 03:11"
  },
  {
    "id": "AC1 041464",
    "content": "PT-AU41",
    "start": "2016-06-18 05:56",
    "end": "2016-06-18 13:32"
  },
  {
    "id": "AC1 041467",
    "content": "PT-AU44",
    "start": "2016-06-20 18:09",
    "end": "2016-06-21 02:48"
  },
  {
    "id": "AC1 041468",
    "content": "PT-AU31",
    "start": "2016-06-21 05:08",
    "end": "2016-06-21 13:39"
  },
  {
    "id": "AC1 041469",
    "content": "PT-AU44",
    "start": "2016-06-21 18:59",
    "end": "2016-06-22 03:38"
  },
  {
    "id": "AC1 041471",
    "content": "PT-AU44",
    "start": "2016-06-22 18:00",
    "end": "2016-06-23 02:39"
  },
  {
    "id": "AC1 041473",
    "content": "PT-AU44",
    "start": "2016-06-23 18:48",
    "end": "2016-06-24 03:20"
  },
  {
    "id": "AC1 041474",
    "content": "PT-AU08",
    "start": "2016-06-24 05:09",
    "end": "2016-06-24 12:56"
  },
  {
    "id": "AC1 041475",
    "content": "PT-AU44",
    "start": "2016-06-24 18:23",
    "end": "2016-06-25 03:02"
  },
  {
    "id": "AC1 041478",
    "content": "PT-AU03",
    "start": "2016-06-27 16:28",
    "end": "2016-06-27 22:30"
  },
  {
    "id": "AC1 041479",
    "content": "PT-AU44",
    "start": "2016-06-28 03:04",
    "end": "2016-06-28 11:21"
  },
  {
    "id": "AC1 041481",
    "content": "PT-AU44",
    "start": "2016-06-29 02:50",
    "end": "2016-06-29 11:06"
  },
  {
    "id": "AC1 041482",
    "content": "PT-AU08",
    "start": "2016-06-29 12:10",
    "end": "2016-06-29 18:02"
  },
  {
    "id": "AC1 041483",
    "content": "PT-AU44",
    "start": "2016-06-30 02:43",
    "end": "2016-06-30 11:21"
  },
  {
    "id": "AC1 041484",
    "content": "PT-AU08",
    "start": "2016-06-30 12:24",
    "end": "2016-06-30 18:56"
  },
  {
    "id": "AC1 041485",
    "content": "PT-AU44",
    "start": "2016-07-01 02:12",
    "end": "2016-07-01 10:49"
  },
  {
    "id": "AC1 041487",
    "content": "PT-AU44",
    "start": "2016-07-02 02:26",
    "end": "2016-07-02 11:06"
  },
  {
    "id": "AC1 041488",
    "content": "PT-AU44",
    "start": "2016-07-02 13:17",
    "end": "2016-07-02 20:48"
  },
  {
    "id": "AC1 041492",
    "content": "PT-AU08",
    "start": "2016-07-04 19:12",
    "end": "2016-07-05 03:53"
  },
  {
    "id": "AC1 041493",
    "content": "PT-AU44",
    "start": "2016-07-05 05:26",
    "end": "2016-07-05 13:54"
  },
  {
    "id": "AC1 041494",
    "content": "PT-AU44",
    "start": "2016-07-05 15:25",
    "end": "2016-07-05 23:01"
  },
  {
    "id": "AC1 041495",
    "content": "PT-AU44",
    "start": "2016-07-06 02:36",
    "end": "2016-07-06 10:57"
  },
  {
    "id": "AC1 041497",
    "content": "PT-AU44",
    "start": "2016-07-07 04:07",
    "end": "2016-07-07 13:08"
  },
  {
    "id": "AC1 041498",
    "content": "PT-AU44",
    "start": "2016-07-07 14:52",
    "end": "2016-07-07 21:37"
  },
  {
    "id": "AC1 041499",
    "content": "PT-AU44",
    "start": "2016-07-08 02:55",
    "end": "2016-07-08 12:02"
  },
  {
    "id": "AC1 041500",
    "content": "PT-AU07",
    "start": "2016-07-08 15:09",
    "end": "2016-07-08 21:21"
  },
  {
    "id": "AC1 041501",
    "content": "PT-AU44",
    "start": "2016-07-09 02:00",
    "end": "2016-07-09 10:19"
  },
  {
    "id": "AC1 041502",
    "content": "PT-AU08",
    "start": "2016-07-09 11:51",
    "end": "2016-07-09 17:53"
  },
  {
    "id": "AC1 041505",
    "content": "PT-AU44",
    "start": "2016-07-11 18:38",
    "end": "2016-07-12 03:28"
  },
  {
    "id": "AC1 041506",
    "content": "PT-AU08",
    "start": "2016-07-12 05:17",
    "end": "2016-07-12 12:08"
  },
  {
    "id": "AC1 041507",
    "content": "PT-AU44",
    "start": "2016-07-12 19:09",
    "end": "2016-07-13 03:48"
  },
  {
    "id": "AC1 041509",
    "content": "PT-AU09",
    "start": "2016-07-13 15:42",
    "end": "2016-07-13 20:54"
  },
  {
    "id": "AC1 041510",
    "content": "PT-AU44",
    "start": "2016-07-13 22:53",
    "end": "2016-07-14 07:34"
  },
  {
    "id": "AC1 041512",
    "content": "PT-AU44",
    "start": "2016-07-14 18:46",
    "end": "2016-07-15 03:28"
  },
  {
    "id": "AC1 041514",
    "content": "PT-AU44",
    "start": "2016-07-15 18:00",
    "end": "2016-07-16 02:14"
  },
  {
    "id": "AC1 041515",
    "content": "PT-AU41",
    "start": "2016-07-16 03:49",
    "end": "2016-07-16 11:40"
  },
  {
    "id": "AC1 041516",
    "content": "PT-AU47",
    "start": "#N/A",
    "end": "#N/A"
  },
  {
    "id": "AC1 041517",
    "content": "PT-AU04",
    "start": "2016-07-18 00:29",
    "end": "2016-07-18 06:57"
  },
  {
    "id": "AC1 041519",
    "content": "PT-AU44",
    "start": "2016-07-18 18:23",
    "end": "2016-07-19 03:34"
  },
  {
    "id": "AC1 041521",
    "content": "PT-AU44",
    "start": "2016-07-19 18:36",
    "end": "2016-07-20 03:40"
  },
  {
    "id": "AC1 041523",
    "content": "PT-AU44",
    "start": "2016-07-20 18:45",
    "end": "2016-07-21 03:43"
  },
  {
    "id": "AC1 041524",
    "content": "PT-AU41",
    "start": "2016-07-21 05:24",
    "end": "2016-07-21 13:35"
  },
  {
    "id": "AC1 041525",
    "content": "PT-AU44",
    "start": "2016-07-21 18:07",
    "end": "2016-07-22 02:58"
  },
  {
    "id": "AC1 041526",
    "content": "PT-AU11",
    "start": "2016-07-22 04:42",
    "end": "2016-07-22 12:45"
  },
  {
    "id": "AC1 041527",
    "content": "PT-AU44",
    "start": "2016-07-22 18:13",
    "end": "2016-07-23 02:44"
  },
  {
    "id": "AC1 041528",
    "content": "PT-AU47",
    "start": "2016-07-23 04:07",
    "end": "2016-07-23 14:09"
  },
  {
    "id": "AC1 041529",
    "content": "PT-AU08",
    "start": "2016-07-23 15:46",
    "end": "2016-07-23 21:55"
  },
  {
    "id": "AC1 041531",
    "content": "PT-AU11",
    "start": "2016-07-26 15:37",
    "end": "2016-07-27 00:09"
  },
  {
    "id": "AC1 041532",
    "content": "PT-AU44",
    "start": "2016-07-27 02:36",
    "end": "2016-07-27 10:58"
  },
  {
    "id": "AC1 041533",
    "content": "PT-AU09",
    "start": "2016-07-27 12:11",
    "end": "2016-07-27 17:12"
  },
  {
    "id": "AC1 041534",
    "content": "PT-AU08",
    "start": "2016-07-27 19:32",
    "end": "2016-07-28 02:00"
  },
  {
    "id": "AC1 041535",
    "content": "PT-AU44",
    "start": "2016-07-28 03:56",
    "end": "2016-07-28 13:07"
  },
  {
    "id": "AC1 041536",
    "content": "PT-AU09",
    "start": "2016-07-28 16:35",
    "end": "2016-07-28 22:53"
  },
  {
    "id": "AC1 041537",
    "content": "PT-AU44",
    "start": "2016-07-29 03:08",
    "end": "2016-07-29 11:52"
  },
  {
    "id": "AC1 041539",
    "content": "PT-AU44",
    "start": "2016-07-30 03:04",
    "end": "2016-07-30 11:45"
  },
  {
    "id": "AC1 041540",
    "content": "PT-AU08",
    "start": "2016-07-30 13:54",
    "end": "2016-07-30 20:14"
  },
  {
    "id": "AC1 041541",
    "content": "PT-AU 28",
    "start": "2016-07-31 07:31",
    "end": "2016-07-31 13:11"
  },
  {
    "id": "AC1 041547",
    "content": "PT-AU44",
    "start": "2016-09-02 02:33",
    "end": "2016-09-02 11:32"
  },
  {
    "id": "AC1 041548",
    "content": "PT-AU44",
    "start": "2016-09-02 18:07",
    "end": "2016-09-03 00:39"
  },
  {
    "id": "AC1 041550",
    "content": "PT-AU04",
    "start": "2016-09-03 13:00",
    "end": "2016-09-03 20:03"
  },
  {
    "id": "AC1 041551",
    "content": "PT-AU44",
    "start": "2016-09-05 18:55",
    "end": "2016-09-06 03:49"
  },
  {
    "id": "AC1 041553",
    "content": "PT-AU44",
    "start": "2016-09-06 18:46",
    "end": "2016-09-07 03:14"
  },
  {
    "id": "AC1 041555",
    "content": "PT-AU44",
    "start": "2016-09-07 19:09",
    "end": "2016-09-08 04:06"
  },
  {
    "id": "AC1 041557",
    "content": "PT-AU44",
    "start": "2016-09-08 19:16",
    "end": "2016-09-09 04:17"
  },
  {
    "id": "AC1 041559",
    "content": "PT-AU44",
    "start": "2016-09-09 18:16",
    "end": "2016-09-10 03:09"
  },
  {
    "id": "AC1 041560",
    "content": "PT-AU41",
    "start": "2016-09-10 05:04",
    "end": "2016-09-10 12:51"
  },
  {
    "id": "AC1 041562",
    "content": "PT-AU 28",
    "start": "2016-09-12 00:28",
    "end": "2016-09-12 07:15"
  },
  {
    "id": "AC1 041563",
    "content": "PT-AU04",
    "start": "2016-09-12 09:47",
    "end": "2016-09-12 16:36"
  },
  {
    "id": "AC1 041564",
    "content": "PT-AU44",
    "start": "2016-09-12 19:00",
    "end": "2016-09-13 03:58"
  },
  {
    "id": "AC1 041566",
    "content": "PT-AU44",
    "start": "2016-09-13 19:00",
    "end": "2016-09-14 03:37"
  },
  {
    "id": "AC1 041568",
    "content": "PT-AU03",
    "start": "2016-09-14 09:37",
    "end": "2016-09-14 15:33"
  },
  {
    "id": "AC1 041569",
    "content": "PT-AU44",
    "start": "2016-09-14 20:33",
    "end": "2016-09-15 05:39"
  },
  {
    "id": "AC1 041570",
    "content": "PT-AU09",
    "start": "2016-09-15 06:42",
    "end": "2016-09-15 11:59"
  },
  {
    "id": "AC1 041571",
    "content": "PT-AU44",
    "start": "2016-09-15 19:02",
    "end": "2016-09-16 03:24"
  },
  {
    "id": "AC1 041573",
    "content": "PT-AU44",
    "start": "2016-09-16 18:11",
    "end": "2016-09-17 02:45"
  },
  {
    "id": "AC1 041575",
    "content": "PT-AU04",
    "start": "2016-09-19 00:46",
    "end": "2016-09-19 09:01"
  },
  {
    "id": "AC1 041577",
    "content": "PT-AU03",
    "start": "2016-09-19 15:57",
    "end": "2016-09-19 21:12"
  },
  {
    "id": "AC1 041578",
    "content": "PT-AU44",
    "start": "2016-09-20 01:44",
    "end": "2016-09-20 10:27"
  },
  {
    "id": "AC1 041579",
    "content": "PT-AU41",
    "start": "2016-09-20 12:19",
    "end": "2016-09-20 12:55"
  },
  {
    "id": "AC1 041580",
    "content": "PT-AU44",
    "start": "2016-09-21 02:02",
    "end": "2016-09-21 10:56"
  },
  {
    "id": "AC1 041581",
    "content": "PT-AU09",
    "start": "2016-09-21 12:13",
    "end": "2016-09-21 17:02"
  },
  {
    "id": "AC1 041582",
    "content": "PT-AU44",
    "start": "2016-09-22 02:04",
    "end": "2016-09-22 10:22"
  },
  {
    "id": "AC1 041583",
    "content": "PT-AU47",
    "start": "2016-09-22 12:57",
    "end": "2016-09-22 22:39"
  },
  {
    "id": "AC1 041584",
    "content": "PT-AU44",
    "start": "2016-09-23 02:00",
    "end": "2016-09-23 10:33"
  },
  {
    "id": "AC1 041585",
    "content": "PT-AU08",
    "start": "2016-09-23 12:17",
    "end": "2016-09-23 12:27"
  },
  {
    "id": "AC1 041586",
    "content": "PT-AU44",
    "start": "2016-09-24 01:42",
    "end": "2016-09-24 10:01"
  },
  {
    "id": "AC1 041587",
    "content": "PT-AU09",
    "start": "2016-09-24 12:45",
    "end": "2016-09-24 17:26"
  },
  {
    "id": "AC1 041588",
    "content": "PT-AU04",
    "start": "2016-09-25 15:45",
    "end": "2016-09-25 23:11"
  },
  {
    "id": "AC1 041589",
    "content": "PT-AU11",
    "start": "2016-09-26 01:00",
    "end": "2016-09-26 09:38"
  },
  {
    "id": "AC1 041590",
    "content": "PT-AU03",
    "start": "2016-09-26 15:13",
    "end": "2016-09-26 21:30"
  },
  {
    "id": "AC1 041591",
    "content": "PT-AU44",
    "start": "2016-09-27 02:06",
    "end": "2016-09-27 10:24"
  },
  {
    "id": "AC1 041593",
    "content": "PT-AU44",
    "start": "2016-09-28 02:02",
    "end": "2016-09-28 10:31"
  },
  {
    "id": "AC1 041594",
    "content": "PT-AU08",
    "start": "2016-09-28 11:32",
    "end": "2016-09-28 17:29"
  },
  {
    "id": "AC1 041595",
    "content": "PT-AU44",
    "start": "2016-09-29 02:28",
    "end": "2016-09-29 10:27"
  },
  {
    "id": "AC1 041596",
    "content": "PT-AU19",
    "start": "2016-09-29 11:28",
    "end": "2016-09-29 21:33"
  },
  {
    "id": "AC1 041597",
    "content": "PT-AU44",
    "start": "2016-09-30 02:14",
    "end": "2016-09-30 10:40"
  },
  {
    "id": "AC1 041599",
    "content": "PT-AU04",
    "start": "2016-09-30 13:45",
    "end": "2016-09-30 21:13"
  },
  {
    "id": "AC1 041600",
    "content": "PT-AU09",
    "start": "2016-09-30 22:01",
    "end": "2016-10-01 02:22"
  },
  {
    "id": "AC1 041601",
    "content": "PT-AU44",
    "start": "2016-10-01 03:51",
    "end": "2016-10-01 12:05"
  },
  {
    "id": "AC1 041602",
    "content": "PT-AU44",
    "start": "2016-10-01 17:40",
    "end": "2016-10-02 00:51"
  },
  {
    "id": "AC1 041605",
    "content": "PT-AU44",
    "start": "2016-10-03 19:34",
    "end": "2016-10-04 04:12"
  },
  {
    "id": "AC1 041607",
    "content": "PT-AU44",
    "start": "2016-10-04 18:05",
    "end": "2016-10-05 02:23"
  },
  {
    "id": "AC1 041609",
    "content": "PT-AU44",
    "start": "2016-10-05 18:38",
    "end": "2016-10-06 03:47"
  },
  {
    "id": "AC1 041610",
    "content": "PT-AU44",
    "start": "2016-10-06 18:20",
    "end": "2016-10-07 02:16"
  },
  {
    "id": "AC1 041611",
    "content": "PT-AU47",
    "start": "2016-10-07 03:23",
    "end": "2016-10-07 13:31"
  },
  {
    "id": "AC1 041613",
    "content": "PT-AU44",
    "start": "2016-10-09 00:54",
    "end": "2016-10-09 09:57"
  },
  {
    "id": "AC1 041614",
    "content": "PT-AU41",
    "start": "2016-10-09 12:33",
    "end": "2016-10-09 20:00"
  },
  {
    "id": "AC1 041615",
    "content": "PT-AU08",
    "start": "2016-10-09 21:09",
    "end": "2016-10-10 03:57"
  },
  {
    "id": "AC1 041616",
    "content": "PT-AU44",
    "start": "2016-10-10 18:23",
    "end": "2016-10-11 02:36"
  },
  {
    "id": "AC1 041618",
    "content": "PT-AU44",
    "start": "2016-10-11 18:00",
    "end": "2016-10-12 01:52"
  },
  {
    "id": "AC1 041619",
    "content": "PT-AU09",
    "start": "2016-10-12 21:05",
    "end": "2016-10-13 02:35"
  },
  {
    "id": "AC1 041621",
    "content": "PT-AU44",
    "start": "2016-10-13 19:11",
    "end": "2016-10-14 04:16"
  },
  {
    "id": "AC1 041622",
    "content": "PT-AU08",
    "start": "2016-10-14 05:16",
    "end": "2016-10-14 12:04"
  },
  {
    "id": "AC1 041623",
    "content": "PT-AU44",
    "start": "2016-10-14 18:15",
    "end": "2016-10-15 02:29"
  },
  {
    "id": "AC1 041624",
    "content": "PT-AU47",
    "start": "2016-10-15 04:14",
    "end": "2016-10-15 14:35"
  },
  {
    "id": "AC1 041625",
    "content": "PT-AU09",
    "start": "2016-10-15 16:40",
    "end": "2016-10-15 22:49"
  },
  {
    "id": "AC1 041627",
    "content": "PT-AU44",
    "start": "2016-10-18 02:15",
    "end": "2016-10-18 11:19"
  },
  {
    "id": "AC1 041628",
    "content": "PT-AU08",
    "start": "2016-10-18 12:43",
    "end": "2016-10-18 19:10"
  },
  {
    "id": "AC1 041629",
    "content": "PT-AU44",
    "start": "2016-10-19 02:03",
    "end": "2016-10-19 09:58"
  },
  {
    "id": "AC1 041630",
    "content": "PT-AU17",
    "start": "2016-10-19 10:53",
    "end": "2016-10-19 23:24"
  },
  {
    "id": "AC1 041631",
    "content": "PT-AU44",
    "start": "2016-10-20 02:11",
    "end": "2016-10-20 11:04"
  },
  {
    "id": "AC1 041632",
    "content": "PT-AU44",
    "start": "2016-10-20 12:08",
    "end": "2016-10-20 18:48"
  },
  {
    "id": "AC1 041633",
    "content": "PT-AU44",
    "start": "2016-10-21 02:02",
    "end": "2016-10-21 10:06"
  },
  {
    "id": "AC1 041634",
    "content": "PT-AU47",
    "start": "2016-10-21 11:33",
    "end": "2016-10-21 21:00"
  },
  {
    "id": "AC1 041635",
    "content": "PT-AU44",
    "start": "2016-10-22 02:10",
    "end": "2016-10-22 10:41"
  },
  {
    "id": "AC1 041636",
    "content": "PT-AU08",
    "start": "2016-10-22 15:24",
    "end": "2016-10-22 22:28"
  },
  {
    "id": "AC1 041637",
    "content": "PT-AU03",
    "start": "2016-10-23 15:39",
    "end": "2016-10-23 20:51"
  },
  {
    "id": "AC1 041638",
    "content": "PT-AU09",
    "start": "2016-10-23 21:51",
    "end": "2016-10-24 03:04"
  },
  {
    "id": "AC1 041639",
    "content": "PT-AU07",
    "start": "2016-10-24 09:53",
    "end": "2016-10-24 16:13"
  },
  {
    "id": "AC1 041640",
    "content": "PT-AU09",
    "start": "2016-10-24 19:52",
    "end": "2016-10-25 00:46"
  },
  {
    "id": "AC1 041641",
    "content": "PT-AU44",
    "start": "2016-10-25 02:24",
    "end": "2016-10-25 10:56"
  },
  {
    "id": "AC1 041643",
    "content": "PT-AU44",
    "start": "2016-10-26 02:12",
    "end": "2016-10-26 10:50"
  },
  {
    "id": "AC1 041645",
    "content": "PT-AU41",
    "start": "2016-10-27 02:25",
    "end": "2016-10-27 11:02"
  },
  {
    "id": "AC1 041646",
    "content": "PT-AU09",
    "start": "2016-10-27 12:17",
    "end": "2016-10-27 17:23"
  },
  {
    "id": "AC1 041649",
    "content": "PT-AU44",
    "start": "2016-10-29 01:59",
    "end": "2016-10-29 10:24"
  },
  {
    "id": "AC1 041650",
    "content": "PT-AU04",
    "start": "2016-10-29 12:37",
    "end": "2016-10-29 19:43"
  },
  {
    "id": "AC1 041654",
    "content": "PT-AU44",
    "start": "2016-11-02 18:48",
    "end": "2016-11-03 03:13"
  },
  {
    "id": "AC1 041656",
    "content": "PT-AU44",
    "start": "2016-11-03 18:29",
    "end": "2016-11-04 03:26"
  },
  {
    "id": "AC1 041658",
    "content": "PT-AU44",
    "start": "2016-11-04 17:51",
    "end": "2016-11-05 02:44"
  },
  {
    "id": "AC1 041659",
    "content": "PT-AU41",
    "start": "2016-11-05 03:54",
    "end": "2016-11-05 11:14"
  },
  {
    "id": "AC1 041660",
    "content": "PT-AU04",
    "start": "2016-11-05 14:32",
    "end": "2016-11-05 21:28"
  },
  {
    "id": "AC1 041662",
    "content": "PT-AU44",
    "start": "2016-11-07 19:05",
    "end": "2016-11-08 04:06"
  },
  {
    "id": "AC1 041663",
    "content": "PT-AU41",
    "start": "2016-11-08 05:36",
    "end": "2016-11-08 13:37"
  },
  {
    "id": "AC1 041664",
    "content": "PT-AU44",
    "start": "2016-11-08 18:05",
    "end": "2016-11-09 02:35"
  },
  {
    "id": "AC1 041665",
    "content": "PT-AU09",
    "start": "2016-11-09 03:58",
    "end": "2016-11-09 09:18"
  },
  {
    "id": "AC1 041667",
    "content": "PT-AU44",
    "start": "2016-11-09 18:24",
    "end": "2016-11-10 03:16"
  },
  {
    "id": "AC1 041668",
    "content": "PT-AU41",
    "start": "2016-11-10 05:08",
    "end": "2016-11-10 12:30"
  },
  {
    "id": "AC1 041669",
    "content": "PT-AU44",
    "start": "2016-11-10 17:53",
    "end": "2016-11-11 02:10"
  },
  {
    "id": "AC1 041671",
    "content": "PT-AU44",
    "start": "2016-11-11 18:37",
    "end": "2016-11-12 03:18"
  },
  {
    "id": "AC1 041672",
    "content": "PT-AU41",
    "start": "2016-11-12 05:23",
    "end": "2016-11-12 13:25"
  },
  {
    "id": "AC1 041673",
    "content": "PT-AU08",
    "start": "2016-11-12 15:25",
    "end": "2016-11-12 22:02"
  },
  {
    "id": "AC1 041675",
    "content": "PT-AU07",
    "start": "2016-11-14 12:26",
    "end": "2016-11-14 20:11"
  },
  {
    "id": "AC1 041676",
    "content": "PT-AU44",
    "start": "2016-11-15 01:50",
    "end": "2016-11-15 11:05"
  },
  {
    "id": "AC1 041678",
    "content": "PT-AU44",
    "start": "2016-11-16 01:51",
    "end": "2016-11-16 11:33"
  },
  {
    "id": "AC1 041680",
    "content": "PT-AU09",
    "start": "2016-11-16 20:37",
    "end": "2016-11-17 01:44"
  },
  {
    "id": "AC1 041681",
    "content": "PT-AU44",
    "start": "2016-11-17 03:22",
    "end": "2016-11-17 12:09"
  },
  {
    "id": "AC1 041683",
    "content": "PT-AU44",
    "start": "2016-11-18 03:28",
    "end": "2016-11-18 11:50"
  },
  {
    "id": "AC1 041684",
    "content": "PT-AU08",
    "start": "2016-11-18 13:38",
    "end": "2016-11-18 20:29"
  },
  {
    "id": "AC1 041685",
    "content": "PT-AU44",
    "start": "2016-11-19 02:31",
    "end": "2016-11-19 11:18"
  },
  {
    "id": "AC1 041686",
    "content": "PT-AU44",
    "start": "2016-11-20 18:59",
    "end": "2016-11-21 03:34"
  },
  {
    "id": "AC1 041687",
    "content": "PT-AU17",
    "start": "2016-11-21 04:40",
    "end": "2016-11-21 05:31"
  },
  {
    "id": "AC1 041689",
    "content": "PT-AU44",
    "start": "2016-11-22 02:20",
    "end": "2016-11-22 12:13"
  },
  {
    "id": "AC1 041690",
    "content": "PT-AU44",
    "start": "2016-11-22 17:37",
    "end": "2016-11-23 02:23"
  },
  {
    "id": "AC1 041691",
    "content": "PT-AU44",
    "start": "2016-11-23 03:38",
    "end": "2016-11-23 11:51"
  },
  {
    "id": "AC1 041692",
    "content": "PT-AU07",
    "start": "2016-11-23 12:38",
    "end": "2016-11-23 19:19"
  },
  {
    "id": "AC1 041693",
    "content": "PT-AU44",
    "start": "2016-11-24 02:20",
    "end": "2016-11-24 11:42"
  },
  {
    "id": "AC1 041694",
    "content": "PT-AU08",
    "start": "2016-11-24 14:01",
    "end": "2016-11-24 21:26"
  },
  {
    "id": "AC1 041695",
    "content": "PT-AU44",
    "start": "2016-11-25 02:05",
    "end": "2016-11-25 11:01"
  },
  {
    "id": "AC1 041696",
    "content": "PT-AU04",
    "start": "2016-11-25 12:29",
    "end": "2016-11-25 20:48"
  },
  {
    "id": "AC1 041697",
    "content": "PT-AU44",
    "start": "2016-11-26 02:06",
    "end": "2016-11-26 11:17"
  },
  {
    "id": "AC1 041698",
    "content": "PT-AU07",
    "start": "2016-11-26 15:12",
    "end": "2016-11-26 22:51"
  },
  {
    "id": "AC1 041699",
    "content": "PT-AU41",
    "start": "2016-11-28 02:08",
    "end": "2016-11-28 10:55"
  },
  {
    "id": "AC1 041700",
    "content": "PT-AU44",
    "start": "2016-11-28 18:59",
    "end": "2016-11-29 04:09"
  },
  {
    "id": "AC1 041701",
    "content": "PT-AU47",
    "start": "2016-11-29 05:07",
    "end": "2016-11-29 14:06"
  },
  {
    "id": "AC1 041702",
    "content": "PT-AU44",
    "start": "2016-11-29 19:25",
    "end": "2016-11-30 04:48"
  },
  {
    "id": "AC1 041703",
    "content": "PT-AU09",
    "start": "2016-11-30 05:58",
    "end": "2016-11-30 11:21"
  },
  {
    "id": "AC1 041704",
    "content": "PT-AU44",
    "start": "2016-11-30 19:01",
    "end": "2016-12-01 04:02"
  },
  {
    "id": "AC1 041705",
    "content": "PT-AU41",
    "start": "2016-12-01 05:52",
    "end": "2016-12-01 14:47"
  },
  {
    "id": "AC1 041706",
    "content": "PT-AU44",
    "start": "2016-12-01 18:27",
    "end": "2016-12-02 03:42"
  },
  {
    "id": "AC1 041707",
    "content": "PT-AU08",
    "start": "2016-12-02 04:49",
    "end": "2016-12-02 11:55"
  },
  {
    "id": "AC1 041708",
    "content": "PT-AU03",
    "start": "2016-12-02 12:58",
    "end": "2016-12-02 18:29"
  },
  {
    "id": "AC1 041709",
    "content": "PT-AU44",
    "start": "2016-12-02 19:54",
    "end": "2016-12-03 04:36"
  },
  {
    "id": "AC1 041710",
    "content": "PT-AU47",
    "start": "2016-12-03 05:42",
    "end": "2016-12-03 15:27"
  },
  {
    "id": "AC1 041711",
    "content": "PT-AU 28",
    "start": "2016-12-03 16:29",
    "end": "2016-12-03 22:00"
  },
  {
    "id": "AC1 041715",
    "content": "PT-AU44",
    "start": "2016-12-12 18:36",
    "end": "2016-12-13 03:46"
  },
  {
    "id": "AC1 041716",
    "content": "PT-AU41",
    "start": "2016-12-13 05:17",
    "end": "2016-12-13 13:46"
  },
  {
    "id": "AC1 041717",
    "content": "PT-AU44",
    "start": "2016-12-13 17:47",
    "end": "2016-12-14 02:29"
  },
  {
    "id": "AC1 041718",
    "content": "PT-AU19",
    "start": "2016-12-14 03:26",
    "end": "2016-12-14 12:38"
  },
  {
    "id": "AC1 041719",
    "content": "PT-AU44",
    "start": "2016-12-14 18:34",
    "end": "2016-12-15 03:49"
  },
  {
    "id": "AC1 041720",
    "content": "PT-AU47",
    "start": "2016-12-15 05:59",
    "end": "2016-12-15 16:24"
  },
  {
    "id": "AC1 041721",
    "content": "PT-AU44",
    "start": "2016-12-15 18:39",
    "end": "2016-12-16 03:11"
  },
  {
    "id": "AC1 041722",
    "content": "PT-AU04",
    "start": "2016-12-16 04:12",
    "end": "2016-12-16 12:01"
  },
  {
    "id": "AC1 041723",
    "content": "PT-AU44",
    "start": "2016-12-16 20:19",
    "end": "2016-12-17 05:57"
  },
  {
    "id": "AC1 041724",
    "content": "PT-AU 28",
    "start": "2016-12-17 07:51",
    "end": "2016-12-17 14:26"
  },
  {
    "id": "AC1 041725",
    "content": "PT-AU07",
    "start": "2016-12-17 16:40",
    "end": "2016-12-18 01:10"
  },
  {
    "id": "AC1 041726",
    "content": "PT-AU47",
    "start": "2016-12-19 01:30",
    "end": "2016-12-19 10:49"
  },
  {
    "id": "AC1 041727",
    "content": "PT-AU07",
    "start": "2016-12-19 16:34",
    "end": "2016-12-19 23:29"
  },
  {
    "id": "AC1 041729",
    "content": "PT-AU44",
    "start": "2016-12-20 03:30",
    "end": "2016-12-20 12:49"
  },
  {
    "id": "AC1 041731",
    "content": "PT-AU44",
    "start": "2016-12-21 03:34",
    "end": "2016-12-21 13:05"
  },
  {
    "id": "AC1 041732",
    "content": "PT-AU41",
    "start": "2016-12-21 16:09",
    "end": "2016-12-22 00:30"
  },
  {
    "id": "AC1 041733",
    "content": "PT-AU44",
    "start": "2016-12-22 03:05",
    "end": "2016-12-22 12:11"
  },
  {
    "id": "AC1 041735",
    "content": "PT-AU44",
    "start": "2016-12-23 03:13",
    "end": "2016-12-23 12:56"
  },
  {
    "id": "AC1 041736",
    "content": "PT-AU41",
    "start": "2016-12-23 14:53",
    "end": "2016-12-23 23:29"
  },
  {
    "id": "AC1 041737",
    "content": "PT-AU44",
    "start": "2016-12-24 01:47",
    "end": "2016-12-24 09:56"
  },
  {
    "id": "AC1 041739",
    "content": "PT-AU47",
    "start": "2016-12-27 07:38",
    "end": "2016-12-27 18:15"
  },
  {
    "id": "AC1 041740",
    "content": "PT-AU09",
    "start": "2016-12-27 19:54",
    "end": "2016-12-28 00:17"
  },
  {
    "id": "AC1 041741",
    "content": "PT-AU44",
    "start": "2016-12-28 02:50",
    "end": "2016-12-28 12:16"
  },
  {
    "id": "AC1 041742",
    "content": "PT-AU07",
    "start": "2016-12-28 14:40",
    "end": "2016-12-28 20:51"
  },
  {
    "id": "AC1 041743",
    "content": "PT-AU44",
    "start": "2016-12-29 02:08",
    "end": "2016-12-29 10:36"
  },
  {
    "id": "AC1 041744",
    "content": "PT-AU44",
    "start": "2016-12-29 15:01",
    "end": "2016-12-29 23:38"
  },
  {
    "id": "AC1 041745",
    "content": "PT-AU44",
    "start": "2016-12-30 02:47",
    "end": "2016-12-30 12:02"
  },
  {
    "id": "AC1 041746",
    "content": "PT-AU08",
    "start": "2016-12-30 14:50",
    "end": "2016-12-30 21:04"
  },
  {
    "id": "AC1 041747",
    "content": "PT-AU44",
    "start": "2016-12-31 02:42",
    "end": "2016-12-31 11:22"
  },
  {
    "id": "AC1 041748",
    "content": "PT-AU47",
    "start": "2017-01-03 08:16",
    "end": "2017-01-03 18:05"
  },
  {
    "id": "AC1 041749",
    "content": "PT-AU44",
    "start": "2017-01-03 21:10",
    "end": "2017-01-04 06:39"
  },
  {
    "id": "AC1 041750",
    "content": "PT-AU44",
    "start": "2017-01-04 18:34",
    "end": "2017-01-05 03:41"
  },
  {
    "id": "AC1 041751",
    "content": "PT-AU41",
    "start": "2017-01-05 05:10",
    "end": "2017-01-05 13:19"
  },
  {
    "id": "AC1 041752",
    "content": "PT-AU44",
    "start": "2017-01-05 19:15",
    "end": "2017-01-06 04:31"
  },
  {
    "id": "AC1 041753",
    "content": "PT-AU09",
    "start": "2017-01-07 07:41",
    "end": "2017-01-07 12:58"
  },
  {
    "id": "AC1 041754",
    "content": "PT-AU04",
    "start": "2017-01-09 00:04",
    "end": "2017-01-09 07:32"
  },
  {
    "id": "AC1 041757",
    "content": "PT-AU44",
    "start": "2017-01-09 19:31",
    "end": "2017-01-10 04:58"
  },
  {
    "id": "AC1 041758",
    "content": "PT-AU47",
    "start": "2017-01-10 06:17",
    "end": "2017-01-10 15:01"
  },
  {
    "id": "AC1 041759",
    "content": "PT-AU44",
    "start": "2017-01-10 20:16",
    "end": "2017-01-11 06:15"
  },
  {
    "id": "AC1 041760",
    "content": "PT-AU09",
    "start": "2017-01-11 08:15",
    "end": "2017-01-11 13:18"
  },
  {
    "id": "AC1 041761",
    "content": "PT-AU44",
    "start": "2017-01-11 19:27",
    "end": "2017-01-12 04:06"
  },
  {
    "id": "AC1 041762",
    "content": "PT-AU41",
    "start": "2017-01-12 05:49",
    "end": "2017-01-12 14:27"
  },
  {
    "id": "AC1 041763",
    "content": "PT-AU44",
    "start": "2017-01-12 18:56",
    "end": "2017-01-13 04:20"
  },
  {
    "id": "AC1 041764",
    "content": "PT-AU08",
    "start": "2017-01-13 06:02",
    "end": "2017-01-13 13:28"
  },
  {
    "id": "AC1 041765",
    "content": "PT-AU44",
    "start": "2017-01-13 18:23",
    "end": "2017-01-14 03:34"
  },
  {
    "id": "AC1 041766",
    "content": "PT-AU47",
    "start": "2017-01-14 05:24",
    "end": "2017-01-14 15:50"
  },
  {
    "id": "AC1 041767",
    "content": "PT-AU 28",
    "start": "2017-01-14 17:43",
    "end": "2017-01-14 23:39"
  },
  {
    "id": "AC1 041768",
    "content": "PT-AU44",
    "start": "2017-01-16 02:43",
    "end": "2017-01-16 10:56"
  },
  {
    "id": "AC1 041769",
    "content": "PT-AU03",
    "start": "2017-01-16 13:32",
    "end": "2017-01-16 19:23"
  },
  {
    "id": "AC1 041770",
    "content": "PT-AU44",
    "start": "2017-01-17 02:49",
    "end": "2017-01-17 11:40"
  },
  {
    "id": "AC1 041771",
    "content": "PT-AU41",
    "start": "2017-01-17 14:17",
    "end": "2017-01-17 22:27"
  },
  {
    "id": "AC1 041772",
    "content": "PT-AU44",
    "start": "2017-01-18 02:58",
    "end": "2017-01-18 11:40"
  },
  {
    "id": "AC1 041774",
    "content": "PT-AU09",
    "start": "2017-01-18 19:19",
    "end": "2017-01-19 00:20"
  },
  {
    "id": "AC1 041775",
    "content": "PT-AU44",
    "start": "2017-01-19 03:14",
    "end": "2017-01-19 12:48"
  },
  {
    "id": "AC1 041776",
    "content": "PT-AU17",
    "start": "2017-01-19 14:45",
    "end": "2017-01-20 02:00"
  },
  {
    "id": "AC1 041777",
    "content": "PT-AU44",
    "start": "2017-01-20 04:11",
    "end": "2017-01-20 12:38"
  },
  {
    "id": "AC1 041778",
    "content": "PT-AU08",
    "start": "2017-01-20 14:18",
    "end": "2017-01-20 21:21"
  },
  {
    "id": "AC1 041779",
    "content": "PT-AU44",
    "start": "2017-01-21 03:49",
    "end": "2017-01-21 13:01"
  },
  {
    "id": "AC1 041781",
    "content": "PT-AU44",
    "start": "2017-01-23 04:39",
    "end": "2017-01-23 14:26"
  },
  {
    "id": "AC1 041784",
    "content": "PT-AU44",
    "start": "2017-01-24 03:35",
    "end": "2017-01-24 12:38"
  },
  {
    "id": "AC1 041785",
    "content": "PT-AU64",
    "start": "2017-01-24 17:59",
    "end": "2017-01-24 22:14"
  },
  {
    "id": "AC1 041786",
    "content": "PT-AU44",
    "start": "2017-01-25 02:46",
    "end": "2017-01-25 11:48"
  },
  {
    "id": "AC1 041787",
    "content": "PT-AU03",
    "start": "2017-01-25 13:15",
    "end": "2017-01-25 19:12"
  },
  {
    "id": "AC1 041788",
    "content": "PT-AU44",
    "start": "2017-01-26 02:37",
    "end": "2017-01-26 11:03"
  },
  {
    "id": "AC1 041789",
    "content": "PT-AU09",
    "start": "2017-01-26 12:11",
    "end": "2017-01-26 17:14"
  },
  {
    "id": "AC1 041790",
    "content": "PT-AU44",
    "start": "2017-01-27 01:50",
    "end": "2017-01-27 10:58"
  }
]